shell_multiprocess/__init__.py
shell_multiprocess/async_file_logger.py
shell_multiprocess/async_processor.py
shell_multiprocess/cleanup.py
shell_multiprocess/main.py
shell_multiprocess/cmdline_args/__init__.py
shell_multiprocess/cmdline_args/adjuster.py
shell_multiprocess/cmdline_args/parser.py
shell_multiprocess-1.0.2.dist-info/LICENSE
shell_multiprocess-1.0.2.dist-info/METADATA
shell_multiprocess-1.0.2.dist-info/WHEEL
shell_multiprocess-1.0.2.dist-info/entry_points.txt
shell_multiprocess-1.0.2.dist-info/top_level.txt
shell_multiprocess-1.0.2.dist-info/RECORD
