Metadata-Version: 2.1
Name: shell-multiprocess
Version: 1.0.2
Summary: Simple shell script which runs lists of shell commands in parallel
Home-page: UNKNOWN
Author: Kris Urbanczyk
Author-email: urbansanek@gmail.com
License: UNKNOWN
Project-URL: Source Code, https://github.com/urbansan/futures_subproc
Platform: UNKNOWN
Requires-Dist: psutil
Requires-Dist: aiofiles
Requires-Dist: dataclasses ; python_version < "3.7"
